{"PATH":"3\/11749\/details.html","NODES":{"NEW":[{"CORRECT_LABEL":"MethodInvocation","LABEL":"func","LABEL_LOCAL":"func","DATA_TYPE":"Any.func()"}],"OLD":[{"CORRECT_LABEL":"EnhancedForStatement","LABEL":"EnhancedForStatement","LABEL_LOCAL":"F","DATA_TYPE":null},{"CORRECT_LABEL":"Assignment","LABEL":"Assignment:=","LABEL_LOCAL":"½","DATA_TYPE":null}]},"SIZE":3,"Fragments":[{"Email":"stuhood@gmail.com","ProjectName":"pantsbuild\/pants","Author":"Stu Hood","Time":"2016-08-27","Link":"https:\/\/github.com\/pantsbuild\/pants\/commit\/14759e1065e307c7760299670da30f64ffdbf783#diff-8d612681f922f7d6e6d319f8c16181610a4eff7fc745e090588d25a887a8e625L145"},{"Email":"manojkumarsivaraj334@gmail.com","ProjectName":"scikit-optimize\/scikit-optimize","Author":"MechCoder","Time":"2016-04-05","Link":"https:\/\/github.com\/scikit-optimize\/scikit-optimize\/commit\/4af750bec058da0cf5d4a3245a443549b9d7fd33#diff-b664a3975b355614eb5080a28622c74841ee57034e3aa7ccb00c1cb7ff75b571L46"},{"Email":"mark.harfouche@gmail.com","ProjectName":"scikit-image\/scikit-image","Author":"Mark Harfouche","Time":"2018-10-29","Link":"https:\/\/github.com\/scikit-image\/scikit-image\/commit\/7ce950f6379ed53bc982e18132ec63d76f0cdfc5#diff-98ce2e75d377913cfd14c8ca218a085210298e95c759b9aff86dc1bfef9fa291L71"}],"ID":11749,"PATTERN_SIZE":3}