{"PATH":"5\/14726\/details.html","NODES":{"NEW":[{"CORRECT_LABEL":"MethodInvocation","LABEL":"make_doc","LABEL_LOCAL":"make_doc","DATA_TYPE":"Any.make_doc()"},{"CORRECT_LABEL":"MethodInvocation","LABEL":"get_pipe","LABEL_LOCAL":"get_pipe","DATA_TYPE":"Any.get_pipe()"},{"CORRECT_LABEL":"Assignment","LABEL":"Assignment:=","LABEL_LOCAL":"½","DATA_TYPE":null},{"CORRECT_LABEL":"StringLiteral","LABEL":"StringLiteral","LABEL_LOCAL":"-","DATA_TYPE":"String"}],"OLD":[{"CORRECT_LABEL":"AssertStatement","LABEL":"assert","LABEL_LOCAL":"assert","DATA_TYPE":null}]},"SIZE":5,"Fragments":[{"Email":"adrianeboyd@gmail.com","ProjectName":"explosion\/spacy-models","Author":"Adriane Boyd","Time":"2020-09-25","Link":"https:\/\/github.com\/explosion\/spacy-models\/commit\/903180f4a2bc366261f0be102647bb5f23bc073c#diff-24d171212b5833f0ceab142f583eafab5b0dfc2dfe68f6a6865ff65c7d4d65bfL120"},{"Email":"adrianeboyd@gmail.com","ProjectName":"explosion\/spacy-models","Author":"Adriane Boyd","Time":"2020-09-25","Link":"https:\/\/github.com\/explosion\/spacy-models\/commit\/903180f4a2bc366261f0be102647bb5f23bc073c#diff-24d171212b5833f0ceab142f583eafab5b0dfc2dfe68f6a6865ff65c7d4d65bfL114"},{"Email":"adrianeboyd@gmail.com","ProjectName":"explosion\/spacy-models","Author":"Adriane Boyd","Time":"2020-09-25","Link":"https:\/\/github.com\/explosion\/spacy-models\/commit\/903180f4a2bc366261f0be102647bb5f23bc073c#diff-24d171212b5833f0ceab142f583eafab5b0dfc2dfe68f6a6865ff65c7d4d65bfL124"}],"ID":14726,"PATTERN_SIZE":3}