{"PATH":"3\/1540\/details.html","NODES":{"NEW":[{"CORRECT_LABEL":"MethodInvocation","LABEL":"model_from_json","LABEL_LOCAL":"model_from_json","DATA_TYPE":"this.model_from_json()"}],"OLD":[{"CORRECT_LABEL":"MethodInvocation","LABEL":"model_from_json","LABEL_LOCAL":"model_from_json","DATA_TYPE":"this.model_from_json()"},{"CORRECT_LABEL":"Assignment","LABEL":"Assignment:=","LABEL_LOCAL":"½","DATA_TYPE":null}]},"SIZE":3,"Fragments":[{"Email":"francois.chollet@gmail.com","ProjectName":"keras-team\/keras","Author":"Francois Chollet","Time":"2016-07-19","Link":"https:\/\/github.com\/keras-team\/keras\/commit\/946ccd32285ed762743fafce486e7f13d6d4f012#diff-1c16421a8f6eacc2f584e08ac0d4dd2212bfae5b93ce029929c424d35fecfb20L270"},{"Email":"francois.chollet@gmail.com","ProjectName":"keras-team\/keras","Author":"Francois Chollet","Time":"2016-07-19","Link":"https:\/\/github.com\/keras-team\/keras\/commit\/946ccd32285ed762743fafce486e7f13d6d4f012#diff-1c16421a8f6eacc2f584e08ac0d4dd2212bfae5b93ce029929c424d35fecfb20L399"},{"Email":"francois.chollet@gmail.com","ProjectName":"keras-team\/keras","Author":"Francois Chollet","Time":"2016-07-19","Link":"https:\/\/github.com\/keras-team\/keras\/commit\/946ccd32285ed762743fafce486e7f13d6d4f012#diff-1c16421a8f6eacc2f584e08ac0d4dd2212bfae5b93ce029929c424d35fecfb20L211"},{"Email":"francois.chollet@gmail.com","ProjectName":"keras-team\/keras","Author":"Francois Chollet","Time":"2016-07-19","Link":"https:\/\/github.com\/keras-team\/keras\/commit\/946ccd32285ed762743fafce486e7f13d6d4f012#diff-1c16421a8f6eacc2f584e08ac0d4dd2212bfae5b93ce029929c424d35fecfb20L149"},{"Email":"francois.chollet@gmail.com","ProjectName":"keras-team\/keras","Author":"Francois Chollet","Time":"2016-07-19","Link":"https:\/\/github.com\/keras-team\/keras\/commit\/946ccd32285ed762743fafce486e7f13d6d4f012#diff-1c16421a8f6eacc2f584e08ac0d4dd2212bfae5b93ce029929c424d35fecfb20L446"}],"ID":1540,"PATTERN_SIZE":5}