{"PATH":"4\/16689\/details.html","NODES":{"NEW":[{"CORRECT_LABEL":"ArrayInitializer","LABEL":"{}","LABEL_LOCAL":"{}","DATA_TYPE":"{}"},{"CORRECT_LABEL":"Assignment","LABEL":"Assignment:=","LABEL_LOCAL":"½","DATA_TYPE":null},{"CORRECT_LABEL":"Assignment","LABEL":"Assignment:=","LABEL_LOCAL":"½","DATA_TYPE":null}],"OLD":[{"CORRECT_LABEL":"MethodInvocation","LABEL":"embedding","LABEL_LOCAL":"embedding","DATA_TYPE":"CNNClassifier.embedding()"}]},"SIZE":4,"Fragments":[{"Email":"horatio@gmail.com","ProjectName":"stanfordnlp\/stanza","Author":"John Bauer","Time":"2020-06-15","Link":"https:\/\/github.com\/stanfordnlp\/stanza\/commit\/db7b74579181f9cbae3583f447d83148714a1c3d#diff-55f71f149340af323bd01d7015c500cdf779dee0085b5e0dcf1cd7ace79d4610L83"},{"Email":"Tsimfer.SA@gazprom-neft.ru","ProjectName":"analysiscenter\/batchflow","Author":"Sergey Tsimfer","Time":"2019-08-02","Link":"https:\/\/github.com\/analysiscenter\/batchflow\/commit\/4c50261df4847bdfd7c8067307e8532f96d04104#diff-5c1940efe3ee8602b937a2c4626aa04f215d93dae877df60e3d819927a2ee3acL82"},{"Email":"dpressel@gmail.com","ProjectName":"dpressel\/mead-baseline","Author":"dpressel","Time":"2019-09-25","Link":"https:\/\/github.com\/dpressel\/mead-baseline\/commit\/71bd73748b835de5ae20bdc90ce4321e47f4c2b2#diff-56c739f93913ef817fc351cc95027a6046bf8b75e154ee69b54ef8c7c2c3cb21L390"}],"ID":16689,"PATTERN_SIZE":3}