{"PATH":"55\/1963\/details.html","NODES":{"NEW":[{"CORRECT_LABEL":"MethodInvocation","LABEL":"transform_test","LABEL_LOCAL":"transform_test","DATA_TYPE":"this.transform_test()"},{"CORRECT_LABEL":"PyComparator","LABEL":"PyComparator","LABEL_LOCAL":"q","DATA_TYPE":null},{"CORRECT_LABEL":"Assignment","LABEL":"Assignment:=","LABEL_LOCAL":"½","DATA_TYPE":null},{"CORRECT_LABEL":"PyListComprehension","LABEL":"PyListComprehension","LABEL_LOCAL":"m","DATA_TYPE":null},{"CORRECT_LABEL":"SimpleName","LABEL":"SimpleName","LABEL_LOCAL":"*","DATA_TYPE":"Any"},{"CORRECT_LABEL":"MethodInvocation","LABEL":"imread","LABEL_LOCAL":"imread","DATA_TYPE":"mxnet.image.imread()"},{"CORRECT_LABEL":"IfStatement","LABEL":"IfStatement","LABEL_LOCAL":"\u0019","DATA_TYPE":null},{"CORRECT_LABEL":"SimpleName","LABEL":"SimpleName","LABEL_LOCAL":"*","DATA_TYPE":"DUMMY"},{"CORRECT_LABEL":"ReturnStatement","LABEL":"return","LABEL_LOCAL":"return","DATA_TYPE":null},{"CORRECT_LABEL":"Assignment","LABEL":"Assignment:=","LABEL_LOCAL":"½","DATA_TYPE":null},{"CORRECT_LABEL":"SimpleName","LABEL":"SimpleName","LABEL_LOCAL":"*","DATA_TYPE":"DUMMY"}],"OLD":[{"CORRECT_LABEL":"ReturnStatement","LABEL":"return","LABEL_LOCAL":"return","DATA_TYPE":null},{"CORRECT_LABEL":"PyTupleExpression","LABEL":"()","LABEL_LOCAL":"()","DATA_TYPE":"()"},{"CORRECT_LABEL":"ArrayInitializer","LABEL":"{}","LABEL_LOCAL":"{}","DATA_TYPE":"{}"},{"CORRECT_LABEL":"PyTupleExpression","LABEL":"()","LABEL_LOCAL":"()","DATA_TYPE":"()"},{"CORRECT_LABEL":"ArrayInitializer","LABEL":"{}","LABEL_LOCAL":"{}","DATA_TYPE":"{}"},{"CORRECT_LABEL":"ArrayAccess","LABEL":"[]","LABEL_LOCAL":"[]","DATA_TYPE":"Any"},{"CORRECT_LABEL":"NumberLiteral","LABEL":"NumberLiteral","LABEL_LOCAL":"\"","DATA_TYPE":"number"},{"CORRECT_LABEL":"ArrayAccess","LABEL":"[]","LABEL_LOCAL":"[]","DATA_TYPE":"Any"},{"CORRECT_LABEL":"NumberLiteral","LABEL":"NumberLiteral","LABEL_LOCAL":"\"","DATA_TYPE":"number"},{"CORRECT_LABEL":"InfixExpression","LABEL":"InfixExpression:r","LABEL_LOCAL":"ò","DATA_TYPE":null},{"CORRECT_LABEL":"NumberLiteral","LABEL":"NumberLiteral","LABEL_LOCAL":"\"","DATA_TYPE":"number"},{"CORRECT_LABEL":"MethodInvocation","LABEL":"len","LABEL_LOCAL":"len","DATA_TYPE":"this.len()"},{"CORRECT_LABEL":"IfStatement","LABEL":"IfStatement","LABEL_LOCAL":"\u0019","DATA_TYPE":null},{"CORRECT_LABEL":"SimpleName","LABEL":"SimpleName","LABEL_LOCAL":"*","DATA_TYPE":null},{"CORRECT_LABEL":"SimpleName","LABEL":"SimpleName","LABEL_LOCAL":"*","DATA_TYPE":"Any[]"},{"CORRECT_LABEL":"SimpleName","LABEL":"SimpleName","LABEL_LOCAL":"*","DATA_TYPE":"Any[]"},{"CORRECT_LABEL":"Assignment","LABEL":"Assignment:=","LABEL_LOCAL":"½","DATA_TYPE":null},{"CORRECT_LABEL":"Assignment","LABEL":"Assignment:=","LABEL_LOCAL":"½","DATA_TYPE":null},{"CORRECT_LABEL":"MethodInvocation","LABEL":"append","LABEL_LOCAL":"append","DATA_TYPE":"Any[].append()"},{"CORRECT_LABEL":"SimpleName","LABEL":"SimpleName","LABEL_LOCAL":"*","DATA_TYPE":"Any"},{"CORRECT_LABEL":"MethodInvocation","LABEL":"append","LABEL_LOCAL":"append","DATA_TYPE":"Any[].append()"},{"CORRECT_LABEL":"MethodInvocation","LABEL":"asnumpy","LABEL_LOCAL":"asnumpy","DATA_TYPE":"Any.asnumpy()"},{"CORRECT_LABEL":"SimpleName","LABEL":"SimpleName","LABEL_LOCAL":"*","DATA_TYPE":"Any"},{"CORRECT_LABEL":"MethodInvocation","LABEL":"to_tensor","LABEL_LOCAL":"to_tensor","DATA_TYPE":"mxnet.nd.image.to_tensor()"},{"CORRECT_LABEL":"MethodInvocation","LABEL":"expand_dims","LABEL_LOCAL":"expand_dims","DATA_TYPE":"Any.expand_dims()"},{"CORRECT_LABEL":"NumberLiteral","LABEL":"NumberLiteral","LABEL_LOCAL":"\"","DATA_TYPE":"number"},{"CORRECT_LABEL":"FieldAccess","LABEL":"FieldAccess","LABEL_LOCAL":"\u0016","DATA_TYPE":"mxnet.nd.image"},{"CORRECT_LABEL":"FieldAccess","LABEL":"FieldAccess","LABEL_LOCAL":"\u0016","DATA_TYPE":"mxnet.nd"},{"CORRECT_LABEL":"FieldAccess","LABEL":"FieldAccess","LABEL_LOCAL":"\u0016","DATA_TYPE":"mxnet.nd"},{"CORRECT_LABEL":"MethodInvocation","LABEL":"resize_short_within","LABEL_LOCAL":"resize_short_within","DATA_TYPE":"image.resize_short_within()"},{"CORRECT_LABEL":"EnhancedForStatement","LABEL":"EnhancedForStatement","LABEL_LOCAL":"F","DATA_TYPE":null},{"CORRECT_LABEL":"FieldAccess","LABEL":"FieldAccess","LABEL_LOCAL":"\u0016","DATA_TYPE":"mxnet.nd.image"},{"CORRECT_LABEL":"MethodInvocation","LABEL":"normalize","LABEL_LOCAL":"normalize","DATA_TYPE":"mxnet.nd.image.normalize()"},{"CORRECT_LABEL":"Assignment","LABEL":"Assignment:=","LABEL_LOCAL":"½","DATA_TYPE":null},{"CORRECT_LABEL":"Assignment","LABEL":"Assignment:=","LABEL_LOCAL":"½","DATA_TYPE":null},{"CORRECT_LABEL":"Assignment","LABEL":"Assignment:=","LABEL_LOCAL":"½","DATA_TYPE":null},{"CORRECT_LABEL":"Assignment","LABEL":"Assignment:=","LABEL_LOCAL":"½","DATA_TYPE":null},{"CORRECT_LABEL":"Assignment","LABEL":"Assignment:=","LABEL_LOCAL":"½","DATA_TYPE":null},{"CORRECT_LABEL":"MethodInvocation","LABEL":"imread","LABEL_LOCAL":"imread","DATA_TYPE":"mxnet.image.imread()"},{"CORRECT_LABEL":"MethodInvocation","LABEL":"astype","LABEL_LOCAL":"astype","DATA_TYPE":"Any.asnumpy().astype()"},{"CORRECT_LABEL":"StringLiteral","LABEL":"StringLiteral","LABEL_LOCAL":"-","DATA_TYPE":"String"},{"CORRECT_LABEL":"ReturnStatement","LABEL":"return","LABEL_LOCAL":"return","DATA_TYPE":null},{"CORRECT_LABEL":"Assignment","LABEL":"Assignment:=","LABEL_LOCAL":"½","DATA_TYPE":null},{"CORRECT_LABEL":"SimpleName","LABEL":"SimpleName","LABEL_LOCAL":"*","DATA_TYPE":"mxnet"},{"CORRECT_LABEL":"SimpleName","LABEL":"SimpleName","LABEL_LOCAL":"*","DATA_TYPE":"mxnet"},{"CORRECT_LABEL":"SimpleName","LABEL":"SimpleName","LABEL_LOCAL":"*","DATA_TYPE":"Any[]"},{"CORRECT_LABEL":"SimpleName","LABEL":"SimpleName","LABEL_LOCAL":"*","DATA_TYPE":"Any[]"},{"CORRECT_LABEL":"SimpleName","LABEL":"SimpleName","LABEL_LOCAL":"*","DATA_TYPE":"Any[]"},{"CORRECT_LABEL":"SimpleName","LABEL":"SimpleName","LABEL_LOCAL":"*","DATA_TYPE":"Any[]"},{"CORRECT_LABEL":"SimpleName","LABEL":"SimpleName","LABEL_LOCAL":"*","DATA_TYPE":"Any[]"},{"CORRECT_LABEL":"SimpleName","LABEL":"SimpleName","LABEL_LOCAL":"*","DATA_TYPE":"Any[]"},{"CORRECT_LABEL":"SimpleName","LABEL":"SimpleName","LABEL_LOCAL":"*","DATA_TYPE":"Any[]"},{"CORRECT_LABEL":"SimpleName","LABEL":"SimpleName","LABEL_LOCAL":"*","DATA_TYPE":"Any"},{"CORRECT_LABEL":"SimpleName","LABEL":"SimpleName","LABEL_LOCAL":"*","DATA_TYPE":"Any"}]},"SIZE":55,"Fragments":[{"Email":"cheungchih@gmail.com","ProjectName":"dmlc\/gluon-cv","Author":"Joshua Z. Zhang","Time":"2018-10-03","Link":"https:\/\/github.com\/dmlc\/gluon-cv\/commit\/9afdc3cd79162c505526ee638ac64227964005e8#diff-cc2f636fcac2ca56dc27d7cd79619050e284f4256c5c61bd722e377cc2bf74a0L47"},{"Email":"cheungchih@gmail.com","ProjectName":"dmlc\/gluon-cv","Author":"Joshua Z. Zhang","Time":"2018-10-03","Link":"https:\/\/github.com\/dmlc\/gluon-cv\/commit\/9afdc3cd79162c505526ee638ac64227964005e8#diff-6e23228d32b63b9e5026945b49db7aaf9080f205a6a0469a6d433166bb394a49L41"},{"Email":"cheungchih@gmail.com","ProjectName":"dmlc\/gluon-cv","Author":"Joshua Z. Zhang","Time":"2018-10-03","Link":"https:\/\/github.com\/dmlc\/gluon-cv\/commit\/9afdc3cd79162c505526ee638ac64227964005e8#diff-cc2f636fcac2ca56dc27d7cd79619050e284f4256c5c61bd722e377cc2bf74a0L47"},{"Email":"cheungchih@gmail.com","ProjectName":"dmlc\/gluon-cv","Author":"Joshua Z. Zhang","Time":"2018-10-03","Link":"https:\/\/github.com\/dmlc\/gluon-cv\/commit\/9afdc3cd79162c505526ee638ac64227964005e8#diff-e12ccec7d93e9acc633b6f54e523549910fb867732f1873b38b0abcdd89a56b4L42"}],"ID":1963,"PATTERN_SIZE":4}