{"PATH":"3\/25029\/details.html","NODES":{"NEW":[{"CORRECT_LABEL":"MethodInvocation","LABEL":"exp","LABEL_LOCAL":"exp","DATA_TYPE":"numpy.exp()"}],"OLD":[{"CORRECT_LABEL":"MethodInvocation","LABEL":"linspace","LABEL_LOCAL":"linspace","DATA_TYPE":"numpy.linspace()"},{"CORRECT_LABEL":"NumberLiteral","LABEL":"NumberLiteral","LABEL_LOCAL":"\"","DATA_TYPE":"number"}]},"SIZE":3,"Fragments":[{"Email":"mainakjas@gmail.com","ProjectName":"glm-tools\/pyglmnet","Author":"Mainak Jas","Time":"2017-10-27","Link":"https:\/\/github.com\/glm-tools\/pyglmnet\/commit\/4dc03426487168eff54c87ec369085efff3621d2#diff-d62d5b8669b45e84c0fddd3e789fa42ca9c6cd41c328d615f5c12c773dc5db68L227"},{"Email":"dstansby@gmail.com","ProjectName":"matplotlib\/matplotlib","Author":"David Stansby","Time":"2018-02-02","Link":"https:\/\/github.com\/matplotlib\/matplotlib\/commit\/32a2f7931b68e100898eb6c7c2ece2dc3590af82#diff-e03b9654ff9319226d651110ae00d6225c6b3d546f08218cdf78ce94e3aa2367L19"},{"Email":"bryanv@651a555e-23ca-0310-84fe-ca9f7c59d2ea","ProjectName":"enthought\/chaco","Author":"bryanv","Time":"2007-11-29","Link":"https:\/\/github.com\/enthought\/chaco\/commit\/97de926824b3f5cc711c42d6f81f11042b7bad7c#diff-051814865fd77e684913187d39c9569cf2cb6487f16eb3e7544e7add2f690fefL30"}],"ID":25029,"PATTERN_SIZE":3}