{"PATH":"10\/25689\/details.html","NODES":{"NEW":[{"CORRECT_LABEL":"MethodInvocation","LABEL":"len","LABEL_LOCAL":"len","DATA_TYPE":"this.len()"},{"CORRECT_LABEL":"Assignment","LABEL":"Assignment:=","LABEL_LOCAL":"½","DATA_TYPE":null},{"CORRECT_LABEL":"Assignment","LABEL":"Assignment:=","LABEL_LOCAL":"½","DATA_TYPE":null},{"CORRECT_LABEL":"PyTupleExpression","LABEL":"()","LABEL_LOCAL":"()","DATA_TYPE":"()"},{"CORRECT_LABEL":"MethodInvocation","LABEL":"make_iterable","LABEL_LOCAL":"make_iterable","DATA_TYPE":"this.make_iterable()"},{"CORRECT_LABEL":"SimpleName","LABEL":"SimpleName","LABEL_LOCAL":"*","DATA_TYPE":"Any"},{"CORRECT_LABEL":"SimpleName","LABEL":"SimpleName","LABEL_LOCAL":"*","DATA_TYPE":"Any"},{"CORRECT_LABEL":"SimpleName","LABEL":"SimpleName","LABEL_LOCAL":"*","DATA_TYPE":"Any"}],"OLD":[{"CORRECT_LABEL":"MethodInvocation","LABEL":"DataFrame","LABEL_LOCAL":"DataFrame","DATA_TYPE":"pandas.DataFrame()"},{"CORRECT_LABEL":"Assignment","LABEL":"Assignment:=","LABEL_LOCAL":"½","DATA_TYPE":null},{"CORRECT_LABEL":"MethodInvocation","LABEL":"of","LABEL_LOCAL":"of","DATA_TYPE":"Map.of()"},{"CORRECT_LABEL":"StringLiteral","LABEL":"StringLiteral","LABEL_LOCAL":"-","DATA_TYPE":"String"}]},"SIZE":10,"Fragments":[{"Email":"has2k1@gmail.com","ProjectName":"has2k1\/plotnine","Author":"Hassan Kibirige","Time":"2015-04-20","Link":"https:\/\/github.com\/has2k1\/plotnine\/commit\/f41ef99d652c20007e301998603d28de0ac01cdd#diff-f2846d8c10ef97608d85f14e07ae6d4f96c44d3b7d6a107d8860eb1124d9b0b3L19"},{"Email":"has2k1@gmail.com","ProjectName":"has2k1\/plotnine","Author":"Hassan Kibirige","Time":"2015-04-20","Link":"https:\/\/github.com\/has2k1\/plotnine\/commit\/f41ef99d652c20007e301998603d28de0ac01cdd#diff-a9a34a2d1a2b62d4ff6b4a48b5ed152ba09a80e28ced32d8e046016648b559e0L20"},{"Email":"has2k1@gmail.com","ProjectName":"has2k1\/plotnine","Author":"Hassan Kibirige","Time":"2015-04-20","Link":"https:\/\/github.com\/has2k1\/plotnine\/commit\/f41ef99d652c20007e301998603d28de0ac01cdd#diff-19cff64b4d1edb9d0338696982c22c64b428ce7d6413bdaddf7a7543ed1401a5L25"}],"ID":25689,"PATTERN_SIZE":3}