{"PATH":"7\/26649\/details.html","NODES":{"NEW":[{"CORRECT_LABEL":"MethodInvocation","LABEL":"echo","LABEL_LOCAL":"echo","DATA_TYPE":"module.echo()"},{"CORRECT_LABEL":"IfStatement","LABEL":"IfStatement","LABEL_LOCAL":"\u0019","DATA_TYPE":null},{"CORRECT_LABEL":"SimpleName","LABEL":"SimpleName","LABEL_LOCAL":"*","DATA_TYPE":null},{"CORRECT_LABEL":"InfixExpression","LABEL":"InfixExpression:r","LABEL_LOCAL":"ò","DATA_TYPE":null},{"CORRECT_LABEL":"NumberLiteral","LABEL":"NumberLiteral","LABEL_LOCAL":"\"","DATA_TYPE":"number"},{"CORRECT_LABEL":"Assignment","LABEL":"Assignment:=","LABEL_LOCAL":"½","DATA_TYPE":null}],"OLD":[{"CORRECT_LABEL":"MethodInvocation","LABEL":"echo","LABEL_LOCAL":"echo","DATA_TYPE":"module.echo()"}]},"SIZE":7,"Fragments":[{"Email":"mittagessen@l.unchti.me","ProjectName":"mittagessen\/kraken","Author":"Benjamin Kiessling","Time":"2015-09-14","Link":"https:\/\/github.com\/mittagessen\/kraken\/commit\/988f2d40cb058f9540a0e45083acad6a564b28f2#diff-1976283c1acd5b0290d8f589fc2804a90f986f460dd20ffb1a4bbb7b9364a474L76"},{"Email":"mittagessen@l.unchti.me","ProjectName":"mittagessen\/kraken","Author":"Benjamin Kiessling","Time":"2018-03-14","Link":"https:\/\/github.com\/mittagessen\/kraken\/commit\/167641d61ab42c8cd37459dd97d8939e35a859a8#diff-827479ca6d2b6509bfe5d726ebc8dfcac2374c3085053a678adea2ca65e5d524L52"},{"Email":"mittagessen@l.unchti.me","ProjectName":"mittagessen\/kraken","Author":"Benjamin Kiessling","Time":"2018-03-14","Link":"https:\/\/github.com\/mittagessen\/kraken\/commit\/167641d61ab42c8cd37459dd97d8939e35a859a8#diff-1976283c1acd5b0290d8f589fc2804a90f986f460dd20ffb1a4bbb7b9364a474L58"}],"ID":26649,"PATTERN_SIZE":3}