{"PATH":"6\/27091\/details.html","NODES":{"NEW":[{"CORRECT_LABEL":"MethodInvocation","LABEL":"random","LABEL_LOCAL":"random","DATA_TYPE":"this.random()"},{"CORRECT_LABEL":"Assignment","LABEL":"Assignment:=","LABEL_LOCAL":"½","DATA_TYPE":null},{"CORRECT_LABEL":"InfixExpression","LABEL":"InfixExpression:a","LABEL_LOCAL":"á","DATA_TYPE":null},{"CORRECT_LABEL":"Assignment","LABEL":"Assignment:=","LABEL_LOCAL":"½","DATA_TYPE":null},{"CORRECT_LABEL":"Assignment","LABEL":"Assignment:=","LABEL_LOCAL":"½","DATA_TYPE":null}],"OLD":[{"CORRECT_LABEL":"MethodInvocation","LABEL":"astype","LABEL_LOCAL":"astype","DATA_TYPE":"null.astype()"}]},"SIZE":6,"Fragments":[{"Email":"chris.fonnesbeck@vanderbilt.edu","ProjectName":"pymc-devs\/pymc3","Author":"Christopher Fonnesbeck","Time":"2013-05-06","Link":"https:\/\/github.com\/pymc-devs\/pymc3\/commit\/d3443536f3d4e39d5e0b8f90e1f9d0e25af77713#diff-a1db882841d57599b268afdfb2e3f673a80c07093520315ad9c7988611e5299dL163"},{"Email":"takuma.seno@gmail.com","ProjectName":"sony\/nnabla","Author":"takuseno","Time":"2019-01-09","Link":"https:\/\/github.com\/sony\/nnabla\/commit\/0940b083d3cdd0db46c867523e9a58b196e6e9d5#diff-8c0b99a0c7e9d5247ca6f5511b768595172d14d1fce9b36b76b6d74f517b3bf9L30"},{"Email":"chris.fonnesbeck@vanderbilt.edu","ProjectName":"pymc-devs\/pymc3","Author":"Christopher Fonnesbeck","Time":"2013-05-05","Link":"https:\/\/github.com\/pymc-devs\/pymc3\/commit\/120e438fcd6357fc81a979d92b39b2bd7101dd34#diff-a1db882841d57599b268afdfb2e3f673a80c07093520315ad9c7988611e5299dL156"}],"ID":27091,"PATTERN_SIZE":3}