{"PATH":"7\/35661\/details.html","NODES":{"NEW":[{"CORRECT_LABEL":"MethodInvocation","LABEL":"Exception","LABEL_LOCAL":"Exception","DATA_TYPE":"this.Exception()"},{"CORRECT_LABEL":"ThrowStatement","LABEL":"throw","LABEL_LOCAL":"throw","DATA_TYPE":null}],"OLD":[{"CORRECT_LABEL":"MethodInvocation","LABEL":"type","LABEL_LOCAL":"type","DATA_TYPE":"this.type()"},{"CORRECT_LABEL":"MethodInvocation","LABEL":"format","LABEL_LOCAL":"format","DATA_TYPE":"String.format()"},{"CORRECT_LABEL":"ThrowStatement","LABEL":"throw","LABEL_LOCAL":"throw","DATA_TYPE":null},{"CORRECT_LABEL":"StringLiteral","LABEL":"StringLiteral","LABEL_LOCAL":"-","DATA_TYPE":"String"},{"CORRECT_LABEL":"MethodInvocation","LABEL":"Exception","LABEL_LOCAL":"Exception","DATA_TYPE":"this.Exception()"}]},"SIZE":7,"Fragments":[{"Email":"yhcao6@gmail.com","ProjectName":"open-mmlab\/mmcv","Author":"Cao Yuhang","Time":"2020-04-25","Link":"https:\/\/github.com\/open-mmlab\/mmcv\/commit\/b7e8d7d7fb49ae7a66fce7e6ee1f0cbaf561e7d6#diff-81dbb11b498245309d65fe18b43ae273051bde5db6001c09de61086023d5b5b7L27"},{"Email":"yhcao6@gmail.com","ProjectName":"open-mmlab\/mmcv","Author":"Cao Yuhang","Time":"2020-04-25","Link":"https:\/\/github.com\/open-mmlab\/mmcv\/commit\/b7e8d7d7fb49ae7a66fce7e6ee1f0cbaf561e7d6#diff-81dbb11b498245309d65fe18b43ae273051bde5db6001c09de61086023d5b5b7L44"},{"Email":"ericarellano@me.com","ProjectName":"pantsbuild\/pants","Author":"Eric Arellano","Time":"2019-07-24","Link":"https:\/\/github.com\/pantsbuild\/pants\/commit\/4854194228479273a8c86016062d3558321eabec#diff-dac098dd35df1279c52ae183e11cc042d3cbb9929d612e710481818e8ec9718bL28"},{"Email":"yhcao6@gmail.com","ProjectName":"open-mmlab\/mmcv","Author":"Cao Yuhang","Time":"2020-04-25","Link":"https:\/\/github.com\/open-mmlab\/mmcv\/commit\/b7e8d7d7fb49ae7a66fce7e6ee1f0cbaf561e7d6#diff-81dbb11b498245309d65fe18b43ae273051bde5db6001c09de61086023d5b5b7L57"}],"ID":35661,"PATTERN_SIZE":4}