{"PATH":"7\/3771\/details.html","NODES":{"NEW":[{"CORRECT_LABEL":"MethodInvocation","LABEL":"DeserializationError","LABEL_LOCAL":"DeserializationError","DATA_TYPE":"this.DeserializationError()"},{"CORRECT_LABEL":"ThrowStatement","LABEL":"throw","LABEL_LOCAL":"throw","DATA_TYPE":null}],"OLD":[{"CORRECT_LABEL":"PyTupleExpression","LABEL":"()","LABEL_LOCAL":"()","DATA_TYPE":"()"},{"CORRECT_LABEL":"InfixExpression","LABEL":"InfixExpression:a","LABEL_LOCAL":"รก","DATA_TYPE":null},{"CORRECT_LABEL":"MethodInvocation","LABEL":"DeserializationError","LABEL_LOCAL":"DeserializationError","DATA_TYPE":"this.DeserializationError()"},{"CORRECT_LABEL":"ThrowStatement","LABEL":"throw","LABEL_LOCAL":"throw","DATA_TYPE":null},{"CORRECT_LABEL":"StringLiteral","LABEL":"StringLiteral","LABEL_LOCAL":"-","DATA_TYPE":"String"}]},"SIZE":7,"Fragments":[{"Email":"bryan@bokeh.org","ProjectName":"bokeh\/bokeh","Author":"Bryan Van de Ven","Time":"2020-11-01","Link":"https:\/\/github.com\/bokeh\/bokeh\/commit\/531452908b70f7eeb128c955aebe2e4247e5ee08#diff-f86b91d7474144ba719c92b1536e87c7479ca20773d1b8082b95f5c4c17c4916L87"},{"Email":"bryan@bokeh.org","ProjectName":"bokeh\/bokeh","Author":"Bryan Van de Ven","Time":"2020-11-01","Link":"https:\/\/github.com\/bokeh\/bokeh\/commit\/531452908b70f7eeb128c955aebe2e4247e5ee08#diff-19bcbfeec17c62437bf3d70000579cae6caa8a742979e6952026b69794dbf2a7L170"},{"Email":"bryan@bokeh.org","ProjectName":"bokeh\/bokeh","Author":"Bryan Van de Ven","Time":"2020-11-01","Link":"https:\/\/github.com\/bokeh\/bokeh\/commit\/531452908b70f7eeb128c955aebe2e4247e5ee08#diff-862096a17646f5e3729ef7e3362e2e06f39e22d6781a7296a90640acdea222cbL458"},{"Email":"bryan@bokeh.org","ProjectName":"bokeh\/bokeh","Author":"Bryan Van de Ven","Time":"2020-11-01","Link":"https:\/\/github.com\/bokeh\/bokeh\/commit\/531452908b70f7eeb128c955aebe2e4247e5ee08#diff-19bcbfeec17c62437bf3d70000579cae6caa8a742979e6952026b69794dbf2a7L285"},{"Email":"bryan@bokeh.org","ProjectName":"bokeh\/bokeh","Author":"Bryan Van de Ven","Time":"2020-11-01","Link":"https:\/\/github.com\/bokeh\/bokeh\/commit\/531452908b70f7eeb128c955aebe2e4247e5ee08#diff-19bcbfeec17c62437bf3d70000579cae6caa8a742979e6952026b69794dbf2a7L66"},{"Email":"bryan@bokeh.org","ProjectName":"bokeh\/bokeh","Author":"Bryan Van de Ven","Time":"2020-11-01","Link":"https:\/\/github.com\/bokeh\/bokeh\/commit\/531452908b70f7eeb128c955aebe2e4247e5ee08#diff-19bcbfeec17c62437bf3d70000579cae6caa8a742979e6952026b69794dbf2a7L229"}],"ID":3771,"PATTERN_SIZE":6}