{"PATH":"9\/41640\/details.html","NODES":{"NEW":[{"CORRECT_LABEL":"PyTupleExpression","LABEL":"()","LABEL_LOCAL":"()","DATA_TYPE":"()"},{"CORRECT_LABEL":"NumberLiteral","LABEL":"NumberLiteral","LABEL_LOCAL":"\"","DATA_TYPE":"number"},{"CORRECT_LABEL":"NumberLiteral","LABEL":"NumberLiteral","LABEL_LOCAL":"\"","DATA_TYPE":"number"},{"CORRECT_LABEL":"NumberLiteral","LABEL":"NumberLiteral","LABEL_LOCAL":"\"","DATA_TYPE":"number"},{"CORRECT_LABEL":"Assignment","LABEL":"Assignment:=","LABEL_LOCAL":"½","DATA_TYPE":null}],"OLD":[{"CORRECT_LABEL":"MethodInvocation","LABEL":"load_dataset","LABEL_LOCAL":"load_dataset","DATA_TYPE":"this.CachedDatasets().load_dataset()"},{"CORRECT_LABEL":"MethodInvocation","LABEL":"CachedDatasets","LABEL_LOCAL":"CachedDatasets","DATA_TYPE":"this.CachedDatasets()"},{"CORRECT_LABEL":"StringLiteral","LABEL":"StringLiteral","LABEL_LOCAL":"-","DATA_TYPE":"String"},{"CORRECT_LABEL":"Assignment","LABEL":"Assignment:=","LABEL_LOCAL":"½","DATA_TYPE":null}]},"SIZE":9,"Fragments":[{"Email":"kushalkolar@gmail.com","ProjectName":"rtavenar\/tslearn","Author":"kushalkolar","Time":"2020-01-22","Link":"https:\/\/github.com\/rtavenar\/tslearn\/commit\/e753bb1b0170eb3d6fabc93311c31f4094f1cdad#diff-f6cd0f3af89f8c88ed79053f8517978c9a56e0c826c3bca4906742a1f8ba7770L130"},{"Email":"kushalkolar@gmail.com","ProjectName":"rtavenar\/tslearn","Author":"kushalkolar","Time":"2020-01-22","Link":"https:\/\/github.com\/rtavenar\/tslearn\/commit\/e753bb1b0170eb3d6fabc93311c31f4094f1cdad#diff-f6cd0f3af89f8c88ed79053f8517978c9a56e0c826c3bca4906742a1f8ba7770L175"},{"Email":"kushalkolar@gmail.com","ProjectName":"rtavenar\/tslearn","Author":"kushalkolar","Time":"2020-01-22","Link":"https:\/\/github.com\/rtavenar\/tslearn\/commit\/e753bb1b0170eb3d6fabc93311c31f4094f1cdad#diff-f6cd0f3af89f8c88ed79053f8517978c9a56e0c826c3bca4906742a1f8ba7770L195"},{"Email":"kushalkolar@gmail.com","ProjectName":"rtavenar\/tslearn","Author":"kushalkolar","Time":"2020-01-22","Link":"https:\/\/github.com\/rtavenar\/tslearn\/commit\/e753bb1b0170eb3d6fabc93311c31f4094f1cdad#diff-f6cd0f3af89f8c88ed79053f8517978c9a56e0c826c3bca4906742a1f8ba7770L212"},{"Email":"kushalkolar@gmail.com","ProjectName":"rtavenar\/tslearn","Author":"kushalkolar","Time":"2020-01-22","Link":"https:\/\/github.com\/rtavenar\/tslearn\/commit\/e753bb1b0170eb3d6fabc93311c31f4094f1cdad#diff-f6cd0f3af89f8c88ed79053f8517978c9a56e0c826c3bca4906742a1f8ba7770L114"}],"ID":41640,"PATTERN_SIZE":5}