{"PATH":"6\/42329\/details.html","NODES":{"NEW":[{"CORRECT_LABEL":"MethodInvocation","LABEL":"exc_info","LABEL_LOCAL":"exc_info","DATA_TYPE":"module.exc_info()"},{"CORRECT_LABEL":"CatchClause","LABEL":"CatchClause","LABEL_LOCAL":"\f","DATA_TYPE":null},{"CORRECT_LABEL":"TryStatement","LABEL":"TryStatement","LABEL_LOCAL":"6","DATA_TYPE":null},{"CORRECT_LABEL":"ArrayAccess","LABEL":"[]","LABEL_LOCAL":"[]","DATA_TYPE":"module.exc_info()[.]"},{"CORRECT_LABEL":"NumberLiteral","LABEL":"NumberLiteral","LABEL_LOCAL":"\"","DATA_TYPE":"number"}],"OLD":[{"CORRECT_LABEL":"IfStatement","LABEL":"IfStatement","LABEL_LOCAL":"\u0019","DATA_TYPE":null}]},"SIZE":6,"Fragments":[{"Email":"fran@aidiq.com","ProjectName":"sahana\/eden","Author":"Fran Boon","Time":"2020-03-20","Link":"https:\/\/github.com\/sahana\/eden\/commit\/824050634fda65bc39e977c23faa6112aa820bd3#diff-0a82ac45515f99a9c99365abcb411ecf6d2b80b5f51c3aa717bdd67ba35e9d27L1825"},{"Email":"fran@aidiq.com","ProjectName":"sahana\/eden","Author":"Fran Boon","Time":"2020-01-27","Link":"https:\/\/github.com\/sahana\/eden\/commit\/2e268c86eee6a1753d16afe23388c9f26dd0f7ca#diff-855ca7a71f924eb614d8fdccab09b01b58b98a196d0a2115088cf5b97ba06103L2517"},{"Email":"coudrn01@bigpurple-ln2.cm.cluster","ProjectName":"ncoudray\/DeepPATH","Author":"Coudray","Time":"2019-11-19","Link":"https:\/\/github.com\/ncoudray\/DeepPATH\/commit\/64c0ea557df21a7585f6fd0fef9d1b0c20f2da3d#diff-6bd7d220ec58a2793509708c4719810dd56f80a819bf7c2f640361ddb04890e9L694"}],"ID":42329,"PATTERN_SIZE":3}