{"PATH":"4\/43547\/details.html","NODES":{"NEW":[{"CORRECT_LABEL":"ArrayAccess","LABEL":"[]","LABEL_LOCAL":"[]","DATA_TYPE":"CoursierSubsystem._default_urls[.]"}],"OLD":[{"CORRECT_LABEL":"MethodInvocation","LABEL":"register","LABEL_LOCAL":"register","DATA_TYPE":"this.register()"},{"CORRECT_LABEL":"StringLiteral","LABEL":"StringLiteral","LABEL_LOCAL":"-","DATA_TYPE":"String"},{"CORRECT_LABEL":"StringLiteral","LABEL":"StringLiteral","LABEL_LOCAL":"-","DATA_TYPE":"String"}]},"SIZE":4,"Fragments":[{"Email":"stuhood@gmail.com","ProjectName":"pantsbuild\/pants","Author":"Stu Hood","Time":"2019-11-17","Link":"https:\/\/github.com\/pantsbuild\/pants\/commit\/7c3389c38fcec91b9c1ae5549cd5afc1098aef66#diff-688df3b3733581ac850ead5d45a2e125c3e51a09fa38de37ea60c362ae5aa586L50"},{"Email":"bergs@janelia.hhmi.org","ProjectName":"ilastik\/ilastik","Author":"Stuart Berg","Time":"2014-03-04","Link":"https:\/\/github.com\/ilastik\/ilastik\/commit\/050b110146f3ce8cb3d3a7cb7ef34363fede1edd#diff-27869580ed18582f2f4e0e49a158d8915d39f46e6bd01744b08ff8a958608386L296"},{"Email":"lamblinp@iro.umontreal.ca","ProjectName":"Theano\/Theano","Author":"Pascal Lamblin","Time":"2017-06-09","Link":"https:\/\/github.com\/Theano\/Theano\/commit\/01922905f9b18acc6f68ebf09960c55894098733#diff-ec13ec5f39ed2a50d5a14f43a8aee820eb6677ef457998ad7b92f2d13db8f171L642"}],"ID":43547,"PATTERN_SIZE":3}