{"PATH":"3\/47821\/details.html","NODES":{"NEW":[{"CORRECT_LABEL":"MethodInvocation","LABEL":"create_optimizer","LABEL_LOCAL":"create_optimizer","DATA_TYPE":"this.create_optimizer()"}],"OLD":[{"CORRECT_LABEL":"ArrayAccess","LABEL":"[]","LABEL_LOCAL":"[]","DATA_TYPE":"Any[.]"},{"CORRECT_LABEL":"StringLiteral","LABEL":"StringLiteral","LABEL_LOCAL":"-","DATA_TYPE":"String"}]},"SIZE":3,"Fragments":[{"Email":"frankchn@google.com","ProjectName":"tensorflow\/tpu","Author":"Frank Chen","Time":"2019-01-22","Link":"https:\/\/github.com\/tensorflow\/tpu\/commit\/2feab9beb8c59f05ca2e1938f484b6bce638af47#diff-e8fd1b066159a6e4f9b1f345791727d453c4ca2ccc3754d570596d7b57d8572fL58"},{"Email":"mikkel@255bits.com","ProjectName":"HyperGAN\/HyperGAN","Author":"Mikkel Garcia","Time":"2020-03-02","Link":"https:\/\/github.com\/HyperGAN\/HyperGAN\/commit\/27761d94f55dfac51152cb26aff4819e7abdde67#diff-c4b00eb5b4d6c5542eb98aa41a6cd437bab494436cc66c8fb56bc84a77eed943L14"},{"Email":"mikkel@255bits.com","ProjectName":"HyperGAN\/HyperGAN","Author":"Mikkel Garcia","Time":"2018-12-20","Link":"https:\/\/github.com\/HyperGAN\/HyperGAN\/commit\/0ffa6f00e5f3385a003df4f27cd944b09103a801#diff-c4b00eb5b4d6c5542eb98aa41a6cd437bab494436cc66c8fb56bc84a77eed943L11"}],"ID":47821,"PATTERN_SIZE":3}