{"PATH":"3\/48109\/details.html","NODES":{"NEW":[{"CORRECT_LABEL":"MethodInvocation","LABEL":"check_array","LABEL_LOCAL":"check_array","DATA_TYPE":"this.check_array()"}],"OLD":[{"CORRECT_LABEL":"ReturnStatement","LABEL":"return","LABEL_LOCAL":"return","DATA_TYPE":null},{"CORRECT_LABEL":"PyTupleExpression","LABEL":"()","LABEL_LOCAL":"()","DATA_TYPE":"()"}]},"SIZE":3,"Fragments":[{"Email":"perimosocordiae@gmail.com","ProjectName":"metric-learn\/metric-learn","Author":"CJ Carey","Time":"2017-03-02","Link":"https:\/\/github.com\/metric-learn\/metric-learn\/commit\/3e38fe09a87e6ef05289f3cbe6ffa03e2dc716e8#diff-2a7f5e957a2e68b9838fc93bbf2efeb966288cb42f9b09fa3f691c6a847edca7L56"},{"Email":"tgsmith61591@gmail.com","ProjectName":"tgsmith61591\/pmdarima","Author":"Taylor Smith","Time":"2018-09-05","Link":"https:\/\/github.com\/tgsmith61591\/pmdarima\/commit\/9253120abe6f429015dbc7b828603e73a50f8c34#diff-65ff653a08bc04cd51ec566cf7b70401a2eee0d3b37e0905df6d2c9a1543d447L490"},{"Email":"sebp@k-d-w.org","ProjectName":"sebp\/scikit-survival","Author":"Sebastian Pölsterl","Time":"2016-12-26","Link":"https:\/\/github.com\/sebp\/scikit-survival\/commit\/95eae9185d8df5dc4d3de030dc19c1d475f18e0f#diff-38b9d937b98bf1b2827297ee581ba79710c79ea7dba657b31e97c7e8454ae639L39"},{"Email":"tgsmith61591@gmail.com","ProjectName":"tgsmith61591\/pmdarima","Author":"tgsmith61591","Time":"2019-11-19","Link":"https:\/\/github.com\/tgsmith61591\/pmdarima\/commit\/11350919148ac860e025264f8dd9fcb6ff8542ff#diff-0a12d00820292864c41b653beb6b88fb1a31723e5b06610586ff8da852494900L89"}],"ID":48109,"PATTERN_SIZE":4}