{"PATH":"10\/48381\/details.html","NODES":{"NEW":[{"CORRECT_LABEL":"MethodInvocation","LABEL":"get_or_create_owner","LABEL_LOCAL":"get_or_create_owner","DATA_TYPE":"Any.get_or_create_owner()"},{"CORRECT_LABEL":"MethodInvocation","LABEL":"load","LABEL_LOCAL":"load","DATA_TYPE":"Any.load()"},{"CORRECT_LABEL":"FieldAccess","LABEL":"FieldAccess","LABEL_LOCAL":"\u0016","DATA_TYPE":"TestConfService.owner"},{"CORRECT_LABEL":"SimpleName","LABEL":"SimpleName","LABEL_LOCAL":"*","DATA_TYPE":"Any"}],"OLD":[{"CORRECT_LABEL":"MethodInvocation","LABEL":"get","LABEL_LOCAL":"get","DATA_TYPE":"Any.objects.get()"},{"CORRECT_LABEL":"FieldAccess","LABEL":"FieldAccess","LABEL_LOCAL":"\u0016","DATA_TYPE":"Any.load().uuid"},{"CORRECT_LABEL":"FieldAccess","LABEL":"FieldAccess","LABEL_LOCAL":"\u0016","DATA_TYPE":"Any.objects"},{"CORRECT_LABEL":"MethodInvocation","LABEL":"load","LABEL_LOCAL":"load","DATA_TYPE":"Any.load()"},{"CORRECT_LABEL":"Assignment","LABEL":"Assignment:=","LABEL_LOCAL":"½","DATA_TYPE":null},{"CORRECT_LABEL":"FieldAccess","LABEL":"FieldAccess","LABEL_LOCAL":"\u0016","DATA_TYPE":"TestConfService.owner"}]},"SIZE":10,"Fragments":[{"Email":"mouradmourafiq@gmail.com","ProjectName":"polyaxon\/polyaxon","Author":"mouradmourafiq","Time":"2019-07-10","Link":"https:\/\/github.com\/polyaxon\/polyaxon\/commit\/5f9c557c99783cbe5d3b21be9ecd95b2e17f8092#diff-6ecf37b08341360ed8b9cec4c8a845d1452fe29e556ab9fb40dae48f8b8f48a2L126"},{"Email":"mouradmourafiq@gmail.com","ProjectName":"polyaxon\/polyaxon","Author":"mouradmourafiq","Time":"2019-07-10","Link":"https:\/\/github.com\/polyaxon\/polyaxon\/commit\/5f9c557c99783cbe5d3b21be9ecd95b2e17f8092#diff-8ae674fd0fe2ba213aae91a08a3b26cb967956bd65ab720223f4131a2549ecd4L28"},{"Email":"mouradmourafiq@gmail.com","ProjectName":"polyaxon\/polyaxon","Author":"mouradmourafiq","Time":"2019-07-10","Link":"https:\/\/github.com\/polyaxon\/polyaxon\/commit\/5f9c557c99783cbe5d3b21be9ecd95b2e17f8092#diff-f8bb5daee9493a3b6a79d382650cb47590df1c4857bb3280fd0674c2188b215dL22"},{"Email":"mouradmourafiq@gmail.com","ProjectName":"polyaxon\/polyaxon","Author":"mouradmourafiq","Time":"2019-07-10","Link":"https:\/\/github.com\/polyaxon\/polyaxon\/commit\/5f9c557c99783cbe5d3b21be9ecd95b2e17f8092#diff-e07b751901e04186274203673705018c3a17988f6531f6f8597c724eb28469afL24"},{"Email":"mouradmourafiq@gmail.com","ProjectName":"polyaxon\/polyaxon","Author":"mouradmourafiq","Time":"2019-07-10","Link":"https:\/\/github.com\/polyaxon\/polyaxon\/commit\/5f9c557c99783cbe5d3b21be9ecd95b2e17f8092#diff-571c2c21dd9a15f3e08209fc7139d9b82e7cb295266d246e8a9e745ad20d47a5L16"},{"Email":"mouradmourafiq@gmail.com","ProjectName":"polyaxon\/polyaxon","Author":"mouradmourafiq","Time":"2019-07-10","Link":"https:\/\/github.com\/polyaxon\/polyaxon\/commit\/5f9c557c99783cbe5d3b21be9ecd95b2e17f8092#diff-9ee78b1b72590dc35b17049eb8b0062f210eec057360a46ba39fd3235cb098d5L63"},{"Email":"mouradmourafiq@gmail.com","ProjectName":"polyaxon\/polyaxon","Author":"mouradmourafiq","Time":"2019-07-10","Link":"https:\/\/github.com\/polyaxon\/polyaxon\/commit\/5f9c557c99783cbe5d3b21be9ecd95b2e17f8092#diff-6ae546ce46114d536ea4a74366f61463268e17c225e83939f08394a5ccec3386L21"},{"Email":"mouradmourafiq@gmail.com","ProjectName":"polyaxon\/polyaxon","Author":"mouradmourafiq","Time":"2019-07-10","Link":"https:\/\/github.com\/polyaxon\/polyaxon\/commit\/5f9c557c99783cbe5d3b21be9ecd95b2e17f8092#diff-315eef981c85e43c48e0ab937aabe7970db553b6294d820257b32910c10c6d64L18"},{"Email":"mouradmourafiq@gmail.com","ProjectName":"polyaxon\/polyaxon","Author":"mouradmourafiq","Time":"2019-07-10","Link":"https:\/\/github.com\/polyaxon\/polyaxon\/commit\/5f9c557c99783cbe5d3b21be9ecd95b2e17f8092#diff-28ea86d0054fa9921f3e2ed5f5d869e02e49687f5f05ac762c73d9a47c3409a9L31"},{"Email":"mouradmourafiq@gmail.com","ProjectName":"polyaxon\/polyaxon","Author":"mouradmourafiq","Time":"2019-07-10","Link":"https:\/\/github.com\/polyaxon\/polyaxon\/commit\/5f9c557c99783cbe5d3b21be9ecd95b2e17f8092#diff-42df4a10464a687c238e37785f457e0c4133624183ba78a91cf4ff4d976b5453L18"}],"ID":48381,"PATTERN_SIZE":10}