{"PATH":"3\/48688\/details.html","NODES":{"NEW":[{"CORRECT_LABEL":"MethodInvocation","LABEL":"get","LABEL_LOCAL":"get","DATA_TYPE":"this.get()"},{"CORRECT_LABEL":"Assignment","LABEL":"Assignment:=","LABEL_LOCAL":"½","DATA_TYPE":null}],"OLD":[{"CORRECT_LABEL":"MethodInvocation","LABEL":"train","LABEL_LOCAL":"train","DATA_TYPE":"ElephasEstimator.train()"}]},"SIZE":3,"Fragments":[{"Email":"max.pumperla@googlemail.com","ProjectName":"maxpumperla\/elephas","Author":"Max Pumperla","Time":"2016-02-23","Link":"https:\/\/github.com\/maxpumperla\/elephas\/commit\/7adb6d43387cd054d10dfafe0b3a6f00ce2e0e4e#diff-67ea69f4f04c1d4feee9d6861239fea510e3e8a79add33bb131c7b84ba9b28a3L47"},{"Email":"hbredin@users.noreply.github.com","ProjectName":"pyannote\/pyannote-audio","Author":"Hervé BREDIN","Time":"2016-11-17","Link":"https:\/\/github.com\/pyannote\/pyannote-audio\/commit\/e234fcf526548d0da6b1180639c9bea92e107fc0#diff-922f646cb9c239ac17275603535dcc77b741085c8f75c23f7d9348ded50b5aeaL177"},{"Email":"gogamza@gmail.com","ProjectName":"dmlc\/gluon-nlp","Author":"Heewon Jeon(gogamza)","Time":"2019-01-29","Link":"https:\/\/github.com\/dmlc\/gluon-nlp\/commit\/d6f719466f1b61ffad90e97ba7573a081054c444#diff-bb03b248700d5d22a6c071289e20db45957077dacee931ca432894a61c7779b5L239"},{"Email":"charlesfisher@Charless-MacBook-Pro.local","ProjectName":"drckf\/paysage","Author":"Charles Fisher","Time":"2016-12-05","Link":"https:\/\/github.com\/drckf\/paysage\/commit\/9cb86cc4d235f259cea36b9349bdd320047aa990#diff-b10564ab7d2c520cdd0243874879fb0a782862c3c902ab535faabe57d5a505e1L11"}],"ID":48688,"PATTERN_SIZE":4}