{"PATH":"6\/51748\/details.html","NODES":{"NEW":[{"CORRECT_LABEL":"MethodInvocation","LABEL":"pow","LABEL_LOCAL":"pow","DATA_TYPE":"Any.pow()"},{"CORRECT_LABEL":"InfixExpression","LABEL":"InfixExpression:a","LABEL_LOCAL":"รก","DATA_TYPE":null},{"CORRECT_LABEL":"InfixExpression","LABEL":"InfixExpression:a","LABEL_LOCAL":"รก","DATA_TYPE":null},{"CORRECT_LABEL":"InfixExpression","LABEL":"InfixExpression:a","LABEL_LOCAL":"รก","DATA_TYPE":null},{"CORRECT_LABEL":"NumberLiteral","LABEL":"NumberLiteral","LABEL_LOCAL":"\"","DATA_TYPE":"number"}],"OLD":[{"CORRECT_LABEL":"MethodInvocation","LABEL":"pow","LABEL_LOCAL":"pow","DATA_TYPE":"Any.pow()"}]},"SIZE":6,"Fragments":[{"Email":"design@kaixhin.com","ProjectName":"pytorch\/examples","Author":"Kaixhin","Time":"2017-10-01","Link":"https:\/\/github.com\/pytorch\/examples\/commit\/9fe431ed5be2ebe43d08d5506a8f8eb690399a80#diff-33ebfafed83bd68e38392ad55cae52465a5c7ac12d5dae5923480085b03adb5bL83"},{"Email":"junyanz@users.noreply.github.com","ProjectName":"junyanz\/BicycleGAN","Author":"Jun-Yan Zhu","Time":"2018-10-25","Link":"https:\/\/github.com\/junyanz\/BicycleGAN\/commit\/4eb1bb9457d53f557fee68a639ae48d5fb539ce3#diff-3ca7434929a648f9dcfde66ac2ba5f180772206c4af14964dbabe1a6caac1c27L157"},{"Email":"petebu@google.com","ProjectName":"deepmind\/sonnet","Author":"Peter Buchlovsky","Time":"2019-06-21","Link":"https:\/\/github.com\/deepmind\/sonnet\/commit\/6436259ca4542e030697c05a72c942aa9aa3ced8#diff-fe93c684c1539af64f13f006226d444f48744b64e9b95253fe2cd6b544d3b8d1L90"}],"ID":51748,"PATTERN_SIZE":3}