{"PATH":"5\/54235\/details.html","NODES":{"NEW":[{"CORRECT_LABEL":"MethodInvocation","LABEL":"has_key","LABEL_LOCAL":"has_key","DATA_TYPE":"Map.has_key()"}],"OLD":[{"CORRECT_LABEL":"ArrayAccess","LABEL":"[]","LABEL_LOCAL":"[]","DATA_TYPE":"UNKNOWN[.]"},{"CORRECT_LABEL":"StringLiteral","LABEL":"StringLiteral","LABEL_LOCAL":"-","DATA_TYPE":"String"},{"CORRECT_LABEL":"FieldAccess","LABEL":"FieldAccess","LABEL_LOCAL":"\u0016","DATA_TYPE":"UNKNOWN"},{"CORRECT_LABEL":"Assignment","LABEL":"Assignment:=","LABEL_LOCAL":"½","DATA_TYPE":null}]},"SIZE":5,"Fragments":[{"Email":"akferoz@esri.com","ProjectName":"Esri\/raster-functions","Author":"Feroz Abdul-Kadar","Time":"2014-08-27","Link":"https:\/\/github.com\/Esri\/raster-functions\/commit\/360fc6fbe7509cc50ae13fe4b952005cbfabd13e#diff-60bd2312abb502fc2afeaeb8e0fcb800f74147265c8d99cb66962f4bf700d88cL121"},{"Email":"akferoz@esri.com","ProjectName":"Esri\/raster-functions","Author":"Feroz Abdul-Kadar","Time":"2015-05-26","Link":"https:\/\/github.com\/Esri\/raster-functions\/commit\/54efdc47f1d5b2952033539fa157e2c3b8b2d586#diff-b2ca1e945a6402cca9c380b27b941600b4f95c2ad2349a29453f73e21dc83867L90"},{"Email":"rsumbaly@esri.com","ProjectName":"Esri\/raster-functions","Author":"Ronak Sumbaly","Time":"2015-05-26","Link":"https:\/\/github.com\/Esri\/raster-functions\/commit\/3a09c2ddfdb1c586f6704363676d6f202c40e65d#diff-b2ca1e945a6402cca9c380b27b941600b4f95c2ad2349a29453f73e21dc83867L103"}],"ID":54235,"PATTERN_SIZE":3}