{"PATH":"6\/54547\/details.html","NODES":{"NEW":[{"CORRECT_LABEL":"PyTupleExpression","LABEL":"()","LABEL_LOCAL":"()","DATA_TYPE":"()"},{"CORRECT_LABEL":"Assignment","LABEL":"Assignment:=","LABEL_LOCAL":"½","DATA_TYPE":null}],"OLD":[{"CORRECT_LABEL":"MethodInvocation","LABEL":"callable","LABEL_LOCAL":"callable","DATA_TYPE":"this.callable()"},{"CORRECT_LABEL":"IfStatement","LABEL":"IfStatement","LABEL_LOCAL":"\u0019","DATA_TYPE":null},{"CORRECT_LABEL":"Assignment","LABEL":"Assignment:=","LABEL_LOCAL":"½","DATA_TYPE":null},{"CORRECT_LABEL":"SimpleName","LABEL":"SimpleName","LABEL_LOCAL":"*","DATA_TYPE":"this.callable()"}]},"SIZE":6,"Fragments":[{"Email":"jonathf@users.noreply.github.com","ProjectName":"jonathf\/chaospy","Author":"Jonathan Feinberg","Time":"2020-11-03","Link":"https:\/\/github.com\/jonathf\/chaospy\/commit\/999d2ff75431496c25c7967b990e6b7fc09bb858#diff-c1ce3035348d0882eca78d15e50b47a3eef6dc9e941f2c47fb619010142ff8fbL115"},{"Email":"m@tthewwithanm.com","ProjectName":"matthewwithanm\/django-imagekit","Author":"Matthew Tretter","Time":"2012-10-17","Link":"https:\/\/github.com\/matthewwithanm\/django-imagekit\/commit\/b0b466618f669f87ecfe66b9dd655415ba88ed83#diff-562edd1c48ced95f40e70dc606e07a92d8aa952a366039a4c4737e1ddddf1d41L16"},{"Email":"alexandre.gramfort@m4x.org","ProjectName":"mne-tools\/mne-python","Author":"Alexandre Gramfort","Time":"2019-04-10","Link":"https:\/\/github.com\/mne-tools\/mne-python\/commit\/cd3f4fb2fe42d99d3eaa2d6a7d1dc56e08d69749#diff-a6032a51226f9175d84fb340bab2a4238ddc24bf0c0f979bd1921f9d2f54c9fbL838"}],"ID":54547,"PATTERN_SIZE":3}