{"PATH":"6\/63406\/details.html","NODES":{"NEW":[{"CORRECT_LABEL":"MethodInvocation","LABEL":"process_request","LABEL_LOCAL":"process_request","DATA_TYPE":"SQLPanelTestCase.panel.process_request()"},{"CORRECT_LABEL":"Assignment","LABEL":"Assignment:=","LABEL_LOCAL":"½","DATA_TYPE":null}],"OLD":[{"CORRECT_LABEL":"MethodInvocation","LABEL":"process_response","LABEL_LOCAL":"process_response","DATA_TYPE":"SQLPanelTestCase.panel.process_response()"},{"CORRECT_LABEL":"FieldAccess","LABEL":"FieldAccess","LABEL_LOCAL":"\u0016","DATA_TYPE":"SQLPanelTestCase.response"},{"CORRECT_LABEL":"FieldAccess","LABEL":"FieldAccess","LABEL_LOCAL":"\u0016","DATA_TYPE":"SQLPanelTestCase.response"},{"CORRECT_LABEL":"SimpleName","LABEL":"SimpleName","LABEL_LOCAL":"*","DATA_TYPE":"SQLPanelTestCase"},{"CORRECT_LABEL":"SimpleName","LABEL":"SimpleName","LABEL_LOCAL":"*","DATA_TYPE":"SQLPanelTestCase"}]},"SIZE":6,"Fragments":[{"Email":"jon.dufresne@gmail.com","ProjectName":"jazzband\/django-debug-toolbar","Author":"Jon Dufresne","Time":"2019-02-24","Link":"https:\/\/github.com\/jazzband\/django-debug-toolbar\/commit\/5299cf826284b6e082c5f18050e4f706faa81c39#diff-4db417a156ab1e6b40b8e02b9d65c17e87b40813db4e220ad1ca3b6fb87afea8L62"},{"Email":"jon.dufresne@gmail.com","ProjectName":"jazzband\/django-debug-toolbar","Author":"Jon Dufresne","Time":"2019-02-24","Link":"https:\/\/github.com\/jazzband\/django-debug-toolbar\/commit\/5299cf826284b6e082c5f18050e4f706faa81c39#diff-4db417a156ab1e6b40b8e02b9d65c17e87b40813db4e220ad1ca3b6fb87afea8L190"},{"Email":"jon.dufresne@gmail.com","ProjectName":"jazzband\/django-debug-toolbar","Author":"Jon Dufresne","Time":"2019-02-24","Link":"https:\/\/github.com\/jazzband\/django-debug-toolbar\/commit\/5299cf826284b6e082c5f18050e4f706faa81c39#diff-4db417a156ab1e6b40b8e02b9d65c17e87b40813db4e220ad1ca3b6fb87afea8L83"},{"Email":"jon.dufresne@gmail.com","ProjectName":"jazzband\/django-debug-toolbar","Author":"Jon Dufresne","Time":"2019-02-24","Link":"https:\/\/github.com\/jazzband\/django-debug-toolbar\/commit\/5299cf826284b6e082c5f18050e4f706faa81c39#diff-4db417a156ab1e6b40b8e02b9d65c17e87b40813db4e220ad1ca3b6fb87afea8L109"},{"Email":"jon.dufresne@gmail.com","ProjectName":"jazzband\/django-debug-toolbar","Author":"Jon Dufresne","Time":"2019-02-24","Link":"https:\/\/github.com\/jazzband\/django-debug-toolbar\/commit\/5299cf826284b6e082c5f18050e4f706faa81c39#diff-4db417a156ab1e6b40b8e02b9d65c17e87b40813db4e220ad1ca3b6fb87afea8L129"},{"Email":"jon.dufresne@gmail.com","ProjectName":"jazzband\/django-debug-toolbar","Author":"Jon Dufresne","Time":"2019-02-24","Link":"https:\/\/github.com\/jazzband\/django-debug-toolbar\/commit\/5299cf826284b6e082c5f18050e4f706faa81c39#diff-5c01b9038bc9c4bc8cda036f9831166a0a65dc3acaf3a8e2ce3a2fd056166a0aL51"},{"Email":"jon.dufresne@gmail.com","ProjectName":"jazzband\/django-debug-toolbar","Author":"Jon Dufresne","Time":"2019-02-24","Link":"https:\/\/github.com\/jazzband\/django-debug-toolbar\/commit\/5299cf826284b6e082c5f18050e4f706faa81c39#diff-cdd1ae7f171aa3ca031c18c114500f52958ccf21ea342cead96f24e63a1ea821L30"},{"Email":"jon.dufresne@gmail.com","ProjectName":"jazzband\/django-debug-toolbar","Author":"Jon Dufresne","Time":"2019-02-24","Link":"https:\/\/github.com\/jazzband\/django-debug-toolbar\/commit\/5299cf826284b6e082c5f18050e4f706faa81c39#diff-f682d95e6598061db2fa04f9765b1c0f661569e4875d5c389bf8a203f38f138cL59"},{"Email":"jon.dufresne@gmail.com","ProjectName":"jazzband\/django-debug-toolbar","Author":"Jon Dufresne","Time":"2019-02-24","Link":"https:\/\/github.com\/jazzband\/django-debug-toolbar\/commit\/5299cf826284b6e082c5f18050e4f706faa81c39#diff-7d429a2df4aff8e62baf8130c770a577df80dc49b98dbfed7894aefdb680f229L34"},{"Email":"jon.dufresne@gmail.com","ProjectName":"jazzband\/django-debug-toolbar","Author":"Jon Dufresne","Time":"2019-02-24","Link":"https:\/\/github.com\/jazzband\/django-debug-toolbar\/commit\/5299cf826284b6e082c5f18050e4f706faa81c39#diff-4db417a156ab1e6b40b8e02b9d65c17e87b40813db4e220ad1ca3b6fb87afea8L43"}],"ID":63406,"PATTERN_SIZE":10}