{"PATH":"6\/65132\/details.html","NODES":{"NEW":[{"CORRECT_LABEL":"MethodInvocation","LABEL":"IndexError","LABEL_LOCAL":"IndexError","DATA_TYPE":"this.IndexError()"},{"CORRECT_LABEL":"ThrowStatement","LABEL":"throw","LABEL_LOCAL":"throw","DATA_TYPE":null}],"OLD":[{"CORRECT_LABEL":"ThrowStatement","LABEL":"throw","LABEL_LOCAL":"throw","DATA_TYPE":null},{"CORRECT_LABEL":"MethodInvocation","LABEL":"IndexError","LABEL_LOCAL":"IndexError","DATA_TYPE":"this.IndexError()"},{"CORRECT_LABEL":"InfixExpression","LABEL":"InfixExpression:a","LABEL_LOCAL":"รก","DATA_TYPE":null},{"CORRECT_LABEL":"FieldAccess","LABEL":"FieldAccess","LABEL_LOCAL":"\u0016","DATA_TYPE":"VideoReader._frame_cnt"}]},"SIZE":6,"Fragments":[{"Email":"yhcao6@gmail.com","ProjectName":"open-mmlab\/mmcv","Author":"Cao Yuhang","Time":"2020-04-25","Link":"https:\/\/github.com\/open-mmlab\/mmcv\/commit\/b7e8d7d7fb49ae7a66fce7e6ee1f0cbaf561e7d6#diff-b93fc0e81f14cc4cbe0264d182f6f47455f42543727988ca3aafa6a20147aa4eL158"},{"Email":"marcel.stimberg@ens.fr","ProjectName":"brian-team\/brian2","Author":"Marcel Stimberg","Time":"2013-07-26","Link":"https:\/\/github.com\/brian-team\/brian2\/commit\/086196a1b4d03de5ed21312d0792419c312d7a36#diff-88053e1807ad7f031394eb20d6494c0fa417a2485e79755faede46effd8f3d3bL263"},{"Email":"marcel.stimberg@ens.fr","ProjectName":"brian-team\/brian2","Author":"Marcel Stimberg","Time":"2013-07-26","Link":"https:\/\/github.com\/brian-team\/brian2\/commit\/086196a1b4d03de5ed21312d0792419c312d7a36#diff-88053e1807ad7f031394eb20d6494c0fa417a2485e79755faede46effd8f3d3bL276"}],"ID":65132,"PATTERN_SIZE":3}