{"PATH":"3\/66893\/details.html","NODES":{"NEW":[{"CORRECT_LABEL":"MethodInvocation","LABEL":"sha1","LABEL_LOCAL":"sha1","DATA_TYPE":"Any.sha1()"},{"CORRECT_LABEL":"Assignment","LABEL":"Assignment:=","LABEL_LOCAL":"½","DATA_TYPE":null}],"OLD":[{"CORRECT_LABEL":"IfStatement","LABEL":"IfStatement","LABEL_LOCAL":"\u0019","DATA_TYPE":null}]},"SIZE":3,"Fragments":[{"Email":"chrisc.101@gmail.com","ProjectName":"ChrisCummins\/clgen","Author":"Chris Cummins","Time":"2019-08-21","Link":"https:\/\/github.com\/ChrisCummins\/clgen\/commit\/3b1bf154144ca1c637471605384c5a438ee6f659#diff-8847c3cd5a9ee9508e28f92dd5bfdf029002238429b84c7cbc813aa044c27aacL206"},{"Email":"sami.kairajarvi@gmail.com","ProjectName":"cve-search\/cve-search","Author":"Sami Kairajarvi","Time":"2019-11-07","Link":"https:\/\/github.com\/cve-search\/cve-search\/commit\/5dc053923afeefed29ce7fc6d56b26a62acac432#diff-5a77e35d325d1b26ac482ace3c39032f4be2e6cb634dc6c42eaa4402ac88e98fL80"},{"Email":"ruihuang@google.com","ProjectName":"GoogleCloudPlatform\/healthcare","Author":"Rui Huang","Time":"2019-06-19","Link":"https:\/\/github.com\/GoogleCloudPlatform\/healthcare\/commit\/ed36cb7118194e02d2eaee2da63e07840b60db8b#diff-724037823e702cfa5e81fa9fb4eb1567c9193f77ecbbe5719bbe8ef924d1c128L32"}],"ID":66893,"PATTERN_SIZE":3}