{"PATH":"4\/67330\/details.html","NODES":{"NEW":[{"CORRECT_LABEL":"MethodInvocation","LABEL":"isnan","LABEL_LOCAL":"isnan","DATA_TYPE":"numpy.isnan()"},{"CORRECT_LABEL":"Assignment","LABEL":"Assignment:=","LABEL_LOCAL":"½","DATA_TYPE":null},{"CORRECT_LABEL":"FieldAccess","LABEL":"FieldAccess","LABEL_LOCAL":"\u0016","DATA_TYPE":"Any.X[.].data"}],"OLD":[{"CORRECT_LABEL":"MethodInvocation","LABEL":"sum","LABEL_LOCAL":"sum","DATA_TYPE":"numpy.sum()"}]},"SIZE":4,"Fragments":[{"Email":"kovacic.andreja@gmail.com","ProjectName":"biolab\/orange3","Author":"Andreja Kovacic","Time":"2019-12-13","Link":"https:\/\/github.com\/biolab\/orange3\/commit\/ce493b09494c007b27c6fbc5944636136fedd6e3#diff-4a0e2be59d2f14fb81aefecc8015c2bd9577b37db0ddc8f92b10eeaa85976e9fL608"},{"Email":"janfreyberg@users.noreply.github.com","ProjectName":"janfreyberg\/superintendent","Author":"Jan Freyberg","Time":"2018-05-31","Link":"https:\/\/github.com\/janfreyberg\/superintendent\/commit\/cb266bbe1ce215ec56cc54ee009ea3a2a055b6d8#diff-39889e42d7579c74458da9e864502404619daebe033d0d7b3b4df2ec04ea6befL38"},{"Email":"pavlin.g.p@gmail.com","ProjectName":"biolab\/orange3","Author":"Pavlin Poličar","Time":"2017-09-09","Link":"https:\/\/github.com\/biolab\/orange3\/commit\/b39db6e2bf0c806554578b5c9895d9b7ef6bd48c#diff-0a4e1aff9fc5f32e34be6837af835ba33ec4f92e0435284ea843c67d19629fc1L15"}],"ID":67330,"PATTERN_SIZE":3}