{"PATH":"5\/7819\/details.html","NODES":{"NEW":[{"CORRECT_LABEL":"MethodInvocation","LABEL":"scope","LABEL_LOCAL":"scope","DATA_TYPE":"Any.scope()"},{"CORRECT_LABEL":"Assignment","LABEL":"Assignment:=","LABEL_LOCAL":"½","DATA_TYPE":null}],"OLD":[{"CORRECT_LABEL":"IfStatement","LABEL":"IfStatement","LABEL_LOCAL":"\u0019","DATA_TYPE":null},{"CORRECT_LABEL":"Assignment","LABEL":"Assignment:=","LABEL_LOCAL":"½","DATA_TYPE":null},{"CORRECT_LABEL":"SimpleName","LABEL":"SimpleName","LABEL_LOCAL":"*","DATA_TYPE":"Any"}]},"SIZE":5,"Fragments":[{"Email":"ankurankan@gmail.com","ProjectName":"pgmpy\/pgmpy","Author":"Ankur Ankan","Time":"2015-02-01","Link":"https:\/\/github.com\/pgmpy\/pgmpy\/commit\/7281b68353fa8f9263e071716ac5081df5168f59#diff-955d28881832469ea2b02793af25ea54cee186fcbfc2828a65539b6e7f566f00L33"},{"Email":"rathodv@google.com","ProjectName":"tensorflow\/models","Author":"Vivek Rathod","Time":"2020-11-06","Link":"https:\/\/github.com\/tensorflow\/models\/commit\/90d1a0bbbca309628e9e8ddc285ca1bf33913eff#diff-d6241ffb0103c18b5bea432efe07a10a271943fbf526fd87b50922a28de1cac5L868"},{"Email":"dpressel@gmail.com","ProjectName":"dpressel\/mead-baseline","Author":"Daniel Pressel","Time":"2021-03-20","Link":"https:\/\/github.com\/dpressel\/mead-baseline\/commit\/a1a5bd048b80b97dbfce02e99571681cda669e7d#diff-5e821e4ee5a9a0b068edfcbcf9d96af7031a03a78db5e956bd926a2c7cf2142fL80"}],"ID":7819,"PATTERN_SIZE":3}